{"name":"git-async","slug":"git-async","owner":"esoftplay","version":"1.0.0","orientation":"portrait","icon":"./assets/icon.png","splash":{"image":"./assets/splash.png","resizeMode":"contain","backgroundColor":"#ffffff"},"runtimeVersion":"gitasync","updates":{"url":"https://ota.fisip.net/api/manifest","enabled":true,"fallbackToCacheTimeout":30000},"assetBundlePatterns":["**/*"],"ios":{"supportsTablet":true,"bundleIdentifier":"com.test.git-async"},"android":{"adaptiveIcon":{"foregroundImage":"./assets/adaptive-icon.png","backgroundColor":"#FFFFFF"},"package":"com.test.gitasync"},"web":{"favicon":"./assets/favicon.png"},"jsEngine":"hermes","extra":{"eas":{"projectId":"a0a03432-e8eb-42cf-96e5-25ce827f3419"}},"sdkVersion":"48.0.0","platforms":["ios","android","web"],"currentFullName":"@esoftplay/git-async","originalFullName":"@esoftplay/git-async"}
